Metadata-Version: 1.2
Name: pasmp
Version: 0.4.0
Summary: Python API for Swift Message Processing
Home-page: https://github.com/cimatch/pasmp
Author: atomsware
Author-email: shimada@atomsware.co.jp
Maintainer: atomsware
Maintainer-email: shimada@atomsware.co.jp
License: MIT
Platform: UNKNOWN
Classifier: Programming Language :: Python :: 2
Classifier: Programming Language :: Python :: 2.7
Classifier: Programming Language :: Python :: 3
Classifier: Programming Language :: Python :: 3.3
Classifier: Programming Language :: Python :: 3.4
Classifier: Programming Language :: Python :: 3.7
Classifier: Programming Language :: Python :: 3.8
Classifier: License :: OSI Approved :: MIT License
